{
  "metadata": {
    "lsmod": "Module                  Size  Used by\nuvcvideo               71309  0 \nvideobuf2_vmalloc      13048  1 uvcvideo\nvideobuf2_memops       13170  1 videobuf2_vmalloc\nvideobuf2_core         39258  1 uvcvideo\nvideodev              108503  2 uvcvideo,videobuf2_core\nnls_iso8859_1          12617  0 \nipt_REJECT             12485  1 \nxt_multiport           12694  1 \niptable_filter         12706  1 \nip_tables              17987  1 iptable_filter\nx_tables               22067  4 ip_tables,xt_multiport,iptable_filter,ipt_REJECT\nctr                    12905  3 \nccm                    17496  3 \ncuse                   13213  3 \nbnep                   18895  2 \nrfcomm                 53664  0 \nbluetooth             342208  10 bnep,rfcomm\ndm_crypt               22589  0 \nbinfmt_misc            13140  1 \ngpio_ich               13229  0 \ndell_laptop            17808  0 \ndcdbas                 14448  1 dell_laptop\nsnd_hda_codec_idt      48978  1 \narc4                   12536  2 \nsnd_hda_intel          42730  3 \nsnd_hda_codec         164067  2 snd_hda_codec_idt,snd_hda_intel\nsnd_hwdep              13272  1 snd_hda_codec\niwl3945                63619  0 \nsnd_pcm                85501  2 snd_hda_codec,snd_hda_intel\niwlegacy               88016  1 iwl3945\nsnd_page_alloc         14230  2 snd_pcm,snd_hda_intel\nmac80211              546067  2 iwl3945,iwlegacy\nsnd_seq_midi           13132  0 \nsnd_seq_midi_event     14475  1 snd_seq_midi\nsnd_rawmidi            25135  1 snd_seq_midi\ncfg80211              409394  3 iwl3945,iwlegacy,mac80211\nsnd_seq                55383  2 snd_seq_midi_event,snd_seq_midi\npcmcia                 51828  0 \nlpc_ich                16864  0 \nsnd_seq_device         14137  3 snd_seq,snd_rawmidi,snd_seq_midi\nyenta_socket           40201  0 \nsnd_timer              28584  2 snd_pcm,snd_seq\ncoretemp               13195  0 \njoydev                 17101  0 \npcmcia_rsrc            18319  1 yenta_socket\nserio_raw              13230  0 \nsnd                    60939  16 snd_hwdep,snd_timer,snd_hda_codec_idt,snd_pcm,snd_seq,snd_rawmidi,snd_hda_codec,snd_hda_intel,snd_seq_device,snd_seq_midi\npcmcia_core            22328  3 pcmcia,pcmcia_rsrc,yenta_socket\nsoundcore              12600  1 snd\nmac_hid                13037  0 \nparport_pc             31981  0 \nppdev                  17391  0 \nlp                     13299  0 \nparport                40836  3 lp,ppdev,parport_pc\nbtrfs                 822702  0 \nxor                    26221  1 btrfs\nraid6_pq               97455  1 btrfs\nlibcrc32c              12543  1 btrfs\nusb_storage            48417  0 \ni915                  710093  3 \ntg3                   152160  0 \npsmouse                91357  0 \ni2c_algo_bit           13197  1 i915\nptp                    18445  1 tg3\ndrm_kms_helper         48868  1 i915\nvideo                  18903  1 i915\ndrm                   244037  4 i915,drm_kms_helper\npps_core               18799  1 ptp", 
    "os-release": "NAME=\"Ubuntu\"\nVERSION=\"14.04.2 LTS, Trusty Tahr\"\nID=ubuntu\nID_LIKE=debian\nPRETTY_NAME=\"Ubuntu 14.04.2 LTS\"\nVERSION_ID=\"14.04\"\nHOME_URL=\"http://www.ubuntu.com/\"\nSUPPORT_URL=\"http://help.ubuntu.com/\"\nBUG_REPORT_URL=\"http://bugs.launchpad.net/ubuntu/\"", 
    "uname": "Linux nisaaz 3.13.0-44-generic #73-Ubuntu SMP Tue Dec 16 00:23:46 UTC 2014 i686 i686 i686 GNU/Linux", 
    "lspci": "00:00.0 Host bridge: Intel Corporation Mobile 945GM/PM/GMS, 943/940GML and 945GT Express Memory Controller Hub (rev 03)\n00:02.0 VGA compatible controller: Intel Corporation Mobile 945GM/GMS, 943/940GML Express Integrated Graphics Controller (rev 03)\n00:02.1 Display controller: Intel Corporation Mobile 945GM/GMS/GME, 943/940GML Express Integrated Graphics Controller (rev 03)\n00:1b.0 Audio device: Intel Corporation NM10/ICH7 Family High Definition Audio Controller (rev 01)\n00:1c.0 PCI bridge: Intel Corporation NM10/ICH7 Family PCI Express Port 1 (rev 01)\n00:1c.1 PCI bridge: Intel Corporation NM10/ICH7 Family PCI Express Port 2 (rev 01)\n00:1c.2 PCI bridge: Intel Corporation NM10/ICH7 Family PCI Express Port 3 (rev 01)\n00:1d.0 USB controller: Intel Corporation NM10/ICH7 Family USB UHCI Controller #1 (rev 01)\n00:1d.1 USB controller: Intel Corporation NM10/ICH7 Family USB UHCI Controller #2 (rev 01)\n00:1d.2 USB controller: Intel Corporation NM10/ICH7 Family USB UHCI Controller #3 (rev 01)\n00:1d.3 USB controller: Intel Corporation NM10/ICH7 Family USB UHCI Controller #4 (rev 01)\n00:1d.7 USB controller: Intel Corporation NM10/ICH7 Family USB2 EHCI Controller (rev 01)\n00:1e.0 PCI bridge: Intel Corporation 82801 Mobile PCI Bridge (rev e1)\n00:1f.0 ISA bridge: Intel Corporation 82801GBM (ICH7-M) LPC Interface Bridge (rev 01)\n00:1f.2 IDE interface: Intel Corporation 82801GBM/GHM (ICH7-M Family) SATA Controller [IDE mode] (rev 01)\n00:1f.3 SMBus: Intel Corporation NM10/ICH7 Family SMBus Controller (rev 01)\n03:01.0 CardBus bridge: O2 Micro, Inc. OZ601/6912/711E0 CardBus/SmartCardBus Controller (rev 40)\n09:00.0 Ethernet controller: Broadcom Corporation NetXtreme BCM5752 Gigabit Ethernet PCI Express (rev 02)\n0c:00.0 Network controller: Intel Corporation PRO/Wireless 3945ABG [Golan] Network Connection (rev 02)"
  }, 
  "backlight": {
    "intel_backlight": {
      "type": "raw", 
      "max_brightness": 312, 
      "brightness": 312, 
      "actual_brightness": 312
    }, 
    "dell_backlight": {
      "type": "platform", 
      "max_brightness": 7, 
      "brightness": 7, 
      "actual_brightness": 7
    }
  }
}